pytorch_show/__init__.py
pytorch_show/main.py
pytorch_show/test.py
pytorch_show/utils.py
pytorch_show-0.1.3.dist-info/METADATA
pytorch_show-0.1.3.dist-info/WHEEL
pytorch_show-0.1.3.dist-info/RECORD
